{
  "mongo_url":"mongodb://userName:password@domain.com:27017,subdomain.domain.com:27017?authSource=admin",
  "mongo_coll_transaction" : "transactions",
  "mongo_coll_block"    : "blocks",
  "mongo_coll_balance"  : "balances", 
  "mongo_coll_target"  : "targets",

  "redis" : {
    "sessionStore" : {
      "host"    :    "127.0.0.1",
      "port"    :    6379
    },
    "MA" : {
      "host"    :    "127.0.0.1",
      "port"    :    7662
    },
    "SL" : {
      "host"    :    "127.0.0.1",
      "port"    :    7675
    }
  },

  "express_port": 8080
}